pykorbit/__init__.py
pykorbit/history.py
pykorbit/private_api.py
pykorbit/public_api.py
pykorbit/websocket.py
pykorbit-0.2.2.dist-info/METADATA
pykorbit-0.2.2.dist-info/WHEEL
pykorbit-0.2.2.dist-info/top_level.txt
pykorbit-0.2.2.dist-info/RECORD
